[{"FName":"Kaylee","LName":"Odom","username":"kaylee.odom@students.fhu.edu","password":"1111"},
{"FName":"Avery","LName":"Harris","username":"avery.harris@students.fhu.edu","password":"2222"},
{"FName":"Priscilla","LName":"Harris","username":"priscilla.harris@students.fhu.edu","password":"3333"},
{"FName":"Abbie","LName":"Vance","username":"abbie.vance@students.fhu.edu","password":"4444"},
{"FName":"Christian","LName":"Stackpole","username":"christian.stackpole@students.fhu.edu","password":"5555"}]